file_cache/__init__.py
file_cache/cache.py
file_cache/utils/__init__.py
file_cache/utils/notebook.py
file_cache/utils/other.py
file_cache/utils/reduce_mem.py
file_cache/utils/tqdm_enhance.py
file_cache/utils/util_date.py
file_cache/utils/util_log.py
file_cache/utils/util_pandas.py
file_cache/utils/visual.py
file_cache-0.2.4.dist-info/METADATA
file_cache-0.2.4.dist-info/WHEEL
file_cache-0.2.4.dist-info/top_level.txt
file_cache-0.2.4.dist-info/RECORD
